<?xml version="1.0"?>
<annotation>
    <folder>images</folder>
    <filename>arrabida-0024.jpg</filename>
    <path>images/arrabida-0024.jpg</path>
    <source>
        <database>Unknown</database>
    </source>
    <size>
        <width>1600</width>
        <height>1167</height>
        <depth>3</depth>
    </size>
    <segmented>0</segmented>
    <object>
        <name>arrabida</name>
        <pose>Unspecified</pose>
        <truncated>0</truncated>
        <difficult>0</difficult>
        <bndbox>
            <xmin>-49.999999999999986</xmin>
            <ymin>-55.999999999999986</ymin>
            <xmax>1573.9999999999995</xmax>
            <ymax>875.9999999999998</ymax>
        </bndbox>
    </object>
</annotation>