<annotation>
  <folder>images</folder>
  <filename>musica-0302.jpg</filename>
  <path>images/musica-0302.jpg</path>
  <source>
    <database>Unknown</database>
  </source>
  <size>
    <width>337</width>
    <height>600</height>
    <depth>3</depth>
  </size>
  <segmented>0</segmented>
  <object>
    <name>musica</name>
    <pose>Unspecified</pose>
    <truncated>0</truncated>
    <difficult>0</difficult>
    <bndbox>
      <xmin>76</xmin>
      <ymin>172</ymin>
      <xmax>321</xmax>
      <ymax>418</ymax>
    </bndbox>
  </object>
</annotation>